helloworld2300.py
helloworld2300-0.0.1.dist-info/METADATA
helloworld2300-0.0.1.dist-info/WHEEL
helloworld2300-0.0.1.dist-info/top_level.txt
helloworld2300-0.0.1.dist-info/RECORD
